[{"id":"f6f2187d.f17ca8","type":"tab","label":"ESP32 - Temperatura e Umidade","disabled":false,"info":""},{"id":"c47b37ab6c72f58e","type":"http in","z":"f6f2187d.f17ca8","name":"ESP32 Data","url":"/data","method":"post","upload":false,"swaggerDoc":"","x":370,"y":220,"wires":[["43d6e8e4900e400a","823296b8ee8ee920"]]},{"id":"43d6e8e4900e400a","type":"json","z":"f6f2187d.f17ca8","name":"Parse JSON","property":"payload","action":"obj","pretty":false,"x":570,"y":220,"wires":[["2b25f6a393f45e21","ebf9c415a909596a","4d18415c127b8ef4","cfe21cfd3edec097"]]},{"id":"2b25f6a393f45e21","type":"debug","z":"f6f2187d.f17ca8","name":"Debug","active":true,"tosidebar":true,"console":false,"tostatus":false,"complete":"payload","targetType":"msg","statusVal":"","statusType":"auto","x":770,"y":160,"wires":[]},{"id":"823296b8ee8ee920","type":"http response","z":"f6f2187d.f17ca8","name":"Response","statusCode":"","headers":{},"x":780,"y":220,"wires":[]},{"id":"ebf9c415a909596a","type":"ui_gauge","z":"f6f2187d.f17ca8","name":"Temperature","group":"ab682f210225433b","order":1,"width":0,"height":0,"gtype":"gage","title":"Temperatura","label":"C","format":"{{msg.payload.temperature}}","min":"-40","max":"50","colors":["#00b500","#e6e600","#ca3838"],"seg1":"30","seg2":"40","diff":false,"className":"","x":790,"y":280,"wires":[]},{"id":"4d18415c127b8ef4","type":"ui_gauge","z":"f6f2187d.f17ca8","name":"Humidity","group":"ab682f210225433b","order":2,"width":0,"height":0,"gtype":"gage","title":"Umidade","label":"%","format":"{{msg.payload.humidity}}","min":0,"max":"100","colors":["#ca3838","#e6e600","#00b500"],"seg1":"25","seg2":"50","diff":false,"className":"","x":780,"y":340,"wires":[]},{"id":"cfe21cfd3edec097","type":"function","z":"f6f2187d.f17ca8","name":"Fomat data for DB","func":"msg.payload = {\n    TableName: \"IoTSensorData\",\n    Item: {\n        SensorID: { S: \"DHT11\" }, \n        Timestamp: { S: new Date().toISOString() }, \n        Temperature: { N: msg.payload.temperature.toString() }, \n        Humidity: { N: msg.payload.humidity.toString() },\n    }\n};\nreturn msg.payload;","outputs":1,"timeout":0,"noerr":0,"initialize":"","finalize":"","libs":[],"x":790,"y":460,"wires":[["52fbc3b9be40d702"]]},{"id":"52fbc3b9be40d702","type":"AWS DynamoDB","z":"f6f2187d.f17ca8","aws":"6e4ea6cf4fd6c2bd","operation":"PutItem","Statements":"","RequestItems":"","TableName":"","BackupName":"","GlobalTableName":"","ReplicationGroup":"","AttributeDefinitions":"","KeySchema":"","BackupArn":"","Key":"","ExportArn":"","Statement":"","TransactStatements":"","TableArn":"","S3Bucket":"","ResourceArn":"","Item":"","TargetTableName":"","Tags":"","TransactItems":"","TagKeys":"","PointInTimeRecoverySpecification":"","ContributorInsightsAction":"","ReplicaUpdates":"","TimeToLiveSpecification":"","name":"","x":1040,"y":460,"wires":[[],["2af97db2b4672e88"]]},{"id":"2af97db2b4672e88","type":"debug","z":"f6f2187d.f17ca8","name":"debug 1","active":true,"tosidebar":true,"console":false,"tostatus":false,"complete":"payload","targetType":"msg","statusVal":"","statusType":"auto","x":1260,"y":460,"wires":[]},{"id":"ab682f210225433b","type":"ui_group","name":"Relatório de Clima","tab":"c2fa53a92d934818","order":1,"disp":true,"width":"6","collapse":false,"className":""},{"id":"6e4ea6cf4fd6c2bd","type":"amazon config","name":"AWS","region":"us-east-2","proxyRequired":false,"proxy":""},{"id":"c2fa53a92d934818","type":"ui_tab","name":"Monitoramento","icon":"dashboard","disabled":false,"hidden":false}]